odoo10_addon_l10n_es_account_invoice_sequence-10.0.1.0.3-py2.7-nspkg.pth
odoo/addons/l10n_es_account_invoice_sequence/README.rst
odoo/addons/l10n_es_account_invoice_sequence/__init__.py
odoo/addons/l10n_es_account_invoice_sequence/__manifest__.py
odoo/addons/l10n_es_account_invoice_sequence/hooks.py
odoo/addons/l10n_es_account_invoice_sequence/data/sequence_data.xml
odoo/addons/l10n_es_account_invoice_sequence/i18n/bg.po
odoo/addons/l10n_es_account_invoice_sequence/i18n/ca.po
odoo/addons/l10n_es_account_invoice_sequence/i18n/es.po
odoo/addons/l10n_es_account_invoice_sequence/i18n/eu.po
odoo/addons/l10n_es_account_invoice_sequence/i18n/gl.po
odoo/addons/l10n_es_account_invoice_sequence/i18n/sl.po
odoo/addons/l10n_es_account_invoice_sequence/models/__init__.py
odoo/addons/l10n_es_account_invoice_sequence/models/account_chart_template.py
odoo/addons/l10n_es_account_invoice_sequence/models/account_invoice.py
odoo/addons/l10n_es_account_invoice_sequence/models/account_journal.py
odoo/addons/l10n_es_account_invoice_sequence/tests/__init__.py
odoo/addons/l10n_es_account_invoice_sequence/tests/test_create_chart.py
odoo/addons/l10n_es_account_invoice_sequence/tests/test_invoice_sequence.py
odoo/addons/l10n_es_account_invoice_sequence/tests/test_other_chart.py
odoo/addons/l10n_es_account_invoice_sequence/views/account_journal_view.xml
odoo/addons/l10n_es_account_invoice_sequence/wizards/__init__.py
odoo/addons/l10n_es_account_invoice_sequence/wizards/wizard_multi_charts_accounts.py
odoo10_addon_l10n_es_account_invoice_sequence-10.0.1.0.3.dist-info/DESCRIPTION.rst
odoo10_addon_l10n_es_account_invoice_sequence-10.0.1.0.3.dist-info/METADATA
odoo10_addon_l10n_es_account_invoice_sequence-10.0.1.0.3.dist-info/RECORD
odoo10_addon_l10n_es_account_invoice_sequence-10.0.1.0.3.dist-info/WHEEL
odoo10_addon_l10n_es_account_invoice_sequence-10.0.1.0.3.dist-info/metadata.json
odoo10_addon_l10n_es_account_invoice_sequence-10.0.1.0.3.dist-info/namespace_packages.txt
odoo10_addon_l10n_es_account_invoice_sequence-10.0.1.0.3.dist-info/top_level.txt
