Metadata-Version: 2.0
Name: odoo10-addon-l10n-es-account-invoice-sequence
Version: 10.0.1.0.3
Summary: Secuencia para facturas separada de la secuencia de asientos
Home-page: https://github.com/OCA/l10n-spain
Author: Spanish Localization Team, NaN·Tic, Trey, Tecnativa, Odoo Community Association (OCA)
Author-email: support@odoo-community.org
License: AGPL-3
Platform: UNKNOWN
Classifier: Programming Language :: Python
Classifier: Framework :: Odoo
Classifier: License :: OSI Approved :: GNU Affero General Public License v3
Requires-Python: ~=2.7
Requires-Dist: odoo (<10.1dev,>=10.0)
